userelaina/__init__.py
userelaina/_archive.py
userelaina/_hash.py
userelaina/_log.py
userelaina/_ls.py
userelaina/_op.py
userelaina/_other.py
userelaina/_pic.py
userelaina/_small.py
userelaina/_th.py
userelaina/code.py
userelaina/pthc.py
userelaina/small.py
userelaina/th.py
userelaina/u.py
userelaina/whoami.py
userelaina-0.0.4.dist-info/LICENSE
userelaina-0.0.4.dist-info/METADATA
userelaina-0.0.4.dist-info/WHEEL
userelaina-0.0.4.dist-info/top_level.txt
userelaina-0.0.4.dist-info/RECORD
