Metadata-Version: 2.1
Name: userelaina
Version: 0.0.4
Summary: Syntax sugar.
Home-page: https://github.com/userelaina
Author: userElaina
Author-email: userElaina@google.com
License: UNKNOWN
Project-URL: Source, https://github.com/userElaina/sugar
Keywords: userelaina
Platform: UNKNOWN
Classifier: License :: OSI Approved :: MIT License
Classifier: Programming Language :: Python :: 3
Classifier: Programming Language :: Python :: 3.6
Classifier: Programming Language :: Python :: 3.7
Classifier: Programming Language :: Python :: 3.8
Classifier: Programming Language :: Python :: 3.9
Requires-Python: >=3.6
License-File: LICENSE
Requires-Dist: numpy
Requires-Dist: pillow
Requires-Dist: opencv-python
Requires-Dist: requests
Requires-Dist: setuptools
